image_processing_EllenRose/__init__.py
image_processing_EllenRose/processing/__init__.py
image_processing_EllenRose/processing/combination.py
image_processing_EllenRose/processing/transformation.py
image_processing_EllenRose/utils/__init__.py
image_processing_EllenRose/utils/io.py
image_processing_EllenRose/utils/plot.py
image_processing_EllenRose-0.0.1.dist-info/METADATA
image_processing_EllenRose-0.0.1.dist-info/WHEEL
image_processing_EllenRose-0.0.1.dist-info/top_level.txt
image_processing_EllenRose-0.0.1.dist-info/RECORD
