Metadata-Version: 2.1
Name: image_processing_EllenRose
Version: 0.0.1
Summary: Dio_Desafio_imagens_Python
Home-page: https://github.com/EllenRose/image-processing-package.git
Author: Ellen
Author-email: ellenrvictoriano@gmail.com
Requires-Dist: matplotlib
Requires-Dist: numpy
Requires-Dist: scikit-image>=0.16.1
